json_reader/__init__.py
json_reader/__main__.py
json_reader/decoder.py
json_reader/decoder_node_py.py
json_reader/test_scanner.py
json_reader-0.3.1.dist-info/METADATA
json_reader-0.3.1.dist-info/WHEEL
json_reader-0.3.1.dist-info/entry_points.txt
json_reader-0.3.1.dist-info/top_level.txt
json_reader-0.3.1.dist-info/RECORD
