Metadata-Version: 2.1
Name: json-reader
Version: 0.3.1
Summary: Read JSON and it's variants from a char stream.
Home-page: https://github.com/weaming/json-reader
Author: weaming
Author-email: garden.yuen@gmail.com
License: UNKNOWN
Project-URL: Source, https://github.com/weaming/json-reader
Project-URL: Bug Reports, https://github.com/weaming/json-reader
Keywords: json,compiler,reader,stream
Platform: UNKNOWN
